pytest_plugins/__init__.py
pytest_plugins/add_config_parameters.py
pytest_plugins/better_report.py
pytest_plugins/fail2skip.py
pytest_plugins/max_fail_streak.py
pytest_plugins/verbose_param_ids.py
pytest_plugins/models/__init__.py
pytest_plugins/models/base_class_test.py
pytest_plugins/models/environment_data.py
pytest_plugins/models/execution_data.py
pytest_plugins/models/status.py
pytest_plugins/models/test_data.py
pytest_plugins/utils/__init__.py
pytest_plugins/utils/create_report.py
pytest_plugins/utils/helper.py
pytest_plugins/utils/pytest_helper.py
pytest_plugins-2.0.1.dist-info/licenses/LICENSE
pytest_plugins-2.0.1.dist-info/METADATA
pytest_plugins-2.0.1.dist-info/WHEEL
pytest_plugins-2.0.1.dist-info/entry_points.txt
pytest_plugins-2.0.1.dist-info/top_level.txt
pytest_plugins-2.0.1.dist-info/RECORD
