Metadata-Version: 2.4
Name: pytest-plugins
Version: 2.0.1
Summary: A Python package for managing pytest plugins.
Author: Avi Zaguri
License: MIT
Project-URL: Homepage, https://github.com/aviz92/pytest-plugins
Project-URL: Repository, https://github.com/aviz92/pytest-plugins
Project-URL: Issues, https://github.com/aviz92/pytest-plugins/issues
Keywords: development,pytest,plugins,testing,automation
Classifier: Development Status :: 5 - Production/Stable
Classifier: Intended Audience :: Developers
Classifier: Framework :: Pytest
Classifier: Programming Language :: Python :: 3.11
Classifier: Operating System :: OS Independent
Requires-Python: >=3.11
License-File: LICENSE
Requires-Dist: build>=1.3.0
Requires-Dist: colorlog>=6.10.1
Requires-Dist: custom-python-logger>=2.0.10
Requires-Dist: pandas>=2.3.3
Requires-Dist: pre-commit>=4.5.0
Requires-Dist: pytest>=9.0.1
Requires-Dist: pytest-rerunfailures>=16.1
Requires-Dist: python-base-toolkit>=0.0.2
Requires-Dist: python-dotenv>=1.2.1
Requires-Dist: setuptools>=80.9.0
Requires-Dist: wheel>=0.45.1
Dynamic: license-file
